odoo/addons/mail_environment_google_gmail/README.rst
odoo/addons/mail_environment_google_gmail/__init__.py
odoo/addons/mail_environment_google_gmail/__manifest__.py
odoo/addons/mail_environment_google_gmail/i18n/it.po
odoo/addons/mail_environment_google_gmail/i18n/mail_environment_google_gmail.pot
odoo/addons/mail_environment_google_gmail/models/__init__.py
odoo/addons/mail_environment_google_gmail/models/ir_mail_server.py
odoo/addons/mail_environment_google_gmail/readme/CONFIGURE.rst
odoo/addons/mail_environment_google_gmail/readme/CONTRIBUTORS.rst
odoo/addons/mail_environment_google_gmail/readme/DESCRIPTION.rst
odoo/addons/mail_environment_google_gmail/static/description/icon.png
odoo/addons/mail_environment_google_gmail/static/description/index.html
odoo14_addon_mail_environment_google_gmail-14.0.1.0.1.dev5.dist-info/METADATA
odoo14_addon_mail_environment_google_gmail-14.0.1.0.1.dev5.dist-info/WHEEL
odoo14_addon_mail_environment_google_gmail-14.0.1.0.1.dev5.dist-info/top_level.txt
odoo14_addon_mail_environment_google_gmail-14.0.1.0.1.dev5.dist-info/RECORD
